smcmodel/__init__.py
smcmodel/core.py
smcmodel/data_pipes.py
smcmodel/shared_constants.py
wf_smcmodel-0.0.1.dist-info/LICENSE
wf_smcmodel-0.0.1.dist-info/METADATA
wf_smcmodel-0.0.1.dist-info/WHEEL
wf_smcmodel-0.0.1.dist-info/top_level.txt
wf_smcmodel-0.0.1.dist-info/RECORD
